{
 "resourcesUrl":"BaseSlot/UHJSlot/resourcesJackpot.data",
 "reelImages":[	
				"reelImages/cherry.png", 
				"reelImages/orange.png", 
				"reelImages/lemon.png",
				"reelImages/plum.png", 
				"reelImages/grapes.png", 
				"reelImages/bell.png",
				"reelImages/watermelon.png", 
				"reelImages/star.png", 
				"reelImages/seven.png"
			   ],
 "smallReelImages":[
				"smallImages/cherry.png", 
				"smallImages/orange.png", 
				"smallImages/lemon.png",
				"smallImages/plum.png", 
				"smallImages/grapes.png", 
				"smallImages/bell.png",
				"smallImages/watermelon.png", 
				"smallImages/star.png", 
				"smallImages/seven.png"
			   ],
 "mainCardsImages":["mainCards/cardBackBlack.png", "mainCards/cardBackRed.png", "mainCards/clubs.png", "mainCards/diamonds.png",
					"mainCards/hearts.png", "mainCards/spades.png", "mainCards/jackImage.png", "mainCards/queenImage.png", "mainCards/kingImage.png", "mainCards/aceImage.png"],
 "gambleCardsImages":["gambleCards/redBack.png", "gambleCards/blackBack.png", "gambleCards/clubs.png", "gambleCards/diamonds.png", "gambleCards/hearts.png", "gambleCards/spades.png"],
 "generalImages":{"background":"background.jpg", "gameTitle":"gameTitle.png", "jackpotBackground":"jackpotImages/jackpotBackground.png", "jackpotBoxes":"jackpotImages/jackpotBoxes.png", "diamond":"diamond.png"},
 "gambleImages":{"gambleBackground":"gambleBackground.png", "gambleWin":"gambleWin.png"},
 "jackpotImages":["jackpotImages/clubs.png", "jackpotImages/diamonds.png", "jackpotImages/hearts.png", "jackpotImages/spades.png",
				  "jackpotImages/clubsInactive.png", "jackpotImages/diamondsInactive.png", "jackpotImages/heartsInactive.png", "jackpotImages/spadesInactive.png",
				  "jackpotImages/clubsActive.png", "jackpotImages/diamondsActive.png", "jackpotImages/heartsActive.png", "jackpotImages/spadesActive.png",
				  "jackpotImages/lightOff.png", "jackpotImages/lightOn.png"],
 "winSounds":["winCherry", "winOrange", "winLemon", "winPlum", "winGrapes", "winBell", "winWatermelon", "winStar", "winSeven"],
 "winFullSounds":[],
 "mainSounds":{"stopReelSingleSound":"stopReelSingle", "stopReelAllSound":"stopReelAll", "collectButtonSound":"collectButton", 
				"mainButtonSound":"mainButton", "startAutoplaySound":"startAuto", "stopAutoplaySound":"stopAuto",  "takeWinSound":"takeWin",
				"creditAnimationSound":"creditAnimation", "currencySound":"currency", "creditSound":"credit", "paytableOpenSound":"paytable", "paytableCloseSound":"paytable", 
				"volumeSound":"volume", "changeLanguageSound":"mainButton", "showDenominationsSound":"showDenominations", "openFullscreenSound":"showDenominations", "closeFullscreenSound":"hideDenominations",
				"hideDenominationsSound":"hideDenominations", "changeDenominationSound":"changeDenomination", "paytableNavigationSound":"paytable", "showLanguagesSound":"showLanguages",
				"hideLanguagesSound":"hideLanguages", "helpOpenSound":"paytable", "gambleOpenSound":"gambleOpen", "gambleCardClickSound":"gambleCardClick",
				"gambleLostSound":"gambleLost", "gambleWonSound":"gambleWon", "jackpotCardOpenSound":"jackpotCardOpen", "jackpotBoxesShowSound":"jackpotBoxesShow",
				"jackpotCardClickSound":"jackpotCardBlink", "jackpotCardFigureMoveSound":"jackpotCardFigureMove", "jackpotCardFigurePulseSound":"jackpotCardFigurePulse", "jackpotBackgroundSound":"jackpotBackground",
				"jackpotShowWinnerSound":"jackpotShowWinner"},
 "scatterSounds":[],
 "enterFreespinsScatterSounds":[],
 "jackpotWinSounds":["jackpotWin1", "jackpotWin2", "jackpotWin3", "jackpotWin4"]
}